CHANGES.txt
CONTRIBUTORS.txt
MANIFEST.in
README.txt
bootstrap.py
buildout.cfg
setup.cfg
setup.py
docs/LICENSE.txt
docs/agpl-3.0.txt
src/wasgehtengine/__init__.py
src/wasgehtengine.import.egg-info/PKG-INFO
src/wasgehtengine.import.egg-info/SOURCES.txt
src/wasgehtengine.import.egg-info/dependency_links.txt
src/wasgehtengine.import.egg-info/entry_points.txt
src/wasgehtengine.import.egg-info/namespace_packages.txt
src/wasgehtengine.import.egg-info/not-zip-safe
src/wasgehtengine.import.egg-info/paster_plugins.txt
src/wasgehtengine.import.egg-info/requires.txt
src/wasgehtengine.import.egg-info/top_level.txt
src/wasgehtengine/import/__init__.py
src/wasgehtengine/import/configure.zcml
src/wasgehtengine/import/crawlpagesexpander.py
src/wasgehtengine/import/event-import.cfg
src/wasgehtengine/import/eventimportdefinitionssource.py
src/wasgehtengine/import/eventimportstatuslogger.py
src/wasgehtengine/import/eventlinksparser.py
src/wasgehtengine/import/eventlistsource.py
src/wasgehtengine/import/eventvalidator.py
src/wasgehtengine/import/htmlparser.py
src/wasgehtengine/import/importform.py
src/wasgehtengine/import/movieresolver.py
src/wasgehtengine/import/osm-venue-import.cfg
src/wasgehtengine/import/osmimportdefinitionssource.py
src/wasgehtengine/import/osmimportstatuslogger.py
src/wasgehtengine/import/osmsource.py
src/wasgehtengine/import/pytransform.py
src/wasgehtengine/import/returnstatus.py
src/wasgehtengine/import/semanticsmatcher.py
src/wasgehtengine/import/urlassembler.py
src/wasgehtengine/import/venueresolver.py
src/wasgehtengine/import/xmlparser.py
src/wasgehtengine/import/xsltransform.py
src/wasgehtengine/import/event_import_definitions/__init__.py
src/wasgehtengine/import/event_import_definitions/facebook.py
src/wasgehtengine/import/importform_templates/importform.pt
src/wasgehtengine/import/profiles/default/metadata.xml
src/wasgehtengine/import/tests/__init__.py
src/wasgehtengine/import/tests/robot_test.txt
src/wasgehtengine/import/tests/test_example.py
src/wasgehtengine/import/tests/test_robot.py